dara/core/__init__.py
dara/core/_assets/__init__.py
dara/core/_assets/auto_js/dara.core.css
dara/core/_assets/auto_js/dara.core.umd.cjs
dara/core/_assets/auto_js/react-dom.development.js
dara/core/_assets/auto_js/react-is.development.js
dara/core/_assets/auto_js/react-query.development.js
dara/core/_assets/auto_js/react.development.js
dara/core/_assets/auto_js/styled-components.min.js
dara/core/_assets/common/jquery.min.js
dara/core/actions.py
dara/core/auth/__init__.py
dara/core/auth/base.py
dara/core/auth/basic.py
dara/core/auth/definitions.py
dara/core/auth/oidc/__init__.py
dara/core/auth/oidc/config.py
dara/core/auth/oidc/definitions.py
dara/core/auth/oidc/routes.py
dara/core/auth/oidc/settings.py
dara/core/auth/oidc/utils.py
dara/core/auth/routes.py
dara/core/auth/utils.py
dara/core/base_definitions.py
dara/core/cli.py
dara/core/configuration.py
dara/core/css.py
dara/core/data_utils.py
dara/core/defaults.py
dara/core/definitions.py
dara/core/http.py
dara/core/interactivity/__init__.py
dara/core/interactivity/actions.py
dara/core/interactivity/any_data_variable.py
dara/core/interactivity/any_variable.py
dara/core/interactivity/client_variable.py
dara/core/interactivity/condition.py
dara/core/interactivity/data_variable.py
dara/core/interactivity/derived_data_variable.py
dara/core/interactivity/derived_variable.py
dara/core/interactivity/filtering.py
dara/core/interactivity/loop_variable.py
dara/core/interactivity/non_data_variable.py
dara/core/interactivity/plain_variable.py
dara/core/interactivity/server_variable.py
dara/core/interactivity/state_variable.py
dara/core/interactivity/stream_event.py
dara/core/interactivity/stream_utils.py
dara/core/interactivity/stream_variable.py
dara/core/interactivity/switch_variable.py
dara/core/interactivity/tabular_variable.py
dara/core/interactivity/url_variable.py
dara/core/internal/__init__.py
dara/core/internal/cache_store/__init__.py
dara/core/internal/cache_store/base_impl.py
dara_core-1.25.1.dist-info/LICENSE
dara_core-1.25.1.dist-info/METADATA
dara_core-1.25.1.dist-info/WHEEL
dara_core-1.25.1.dist-info/entry_points.txt
dara_core-1.25.1.dist-info/RECORD
