Metadata-Version: 2.1
Name: dara-core
Version: 1.25.1
Summary: Dara Framework Core
Home-page: https://dara.causalens.com/
License: Apache-2.0
Author: Sam Smith
Author-email: sam@causalens.com
Requires-Python: >=3.10.0,<3.13.0
Classifier: License :: OSI Approved :: Apache Software License
Classifier: Programming Language :: Python :: 3
Classifier: Programming Language :: Python :: 3.10
Classifier: Programming Language :: Python :: 3.11
Classifier: Programming Language :: Python :: 3.12
Provides-Extra: all
Requires-Dist: aiorwlock (>=1.4.0,<2.0.0)
Requires-Dist: anyio (>=4.0.0)
Requires-Dist: async-asgi-testclient (>=1.4.11,<2.0.0)
Requires-Dist: backoff (>=2.2.1,<3.0.0)
Requires-Dist: cachetools (>=5.0.0)
Requires-Dist: certifi (>=2024.7.4)
Requires-Dist: click (>=8.1.3,<9.0.0)
Requires-Dist: colorama (>=0.4.6,<0.5.0)
Requires-Dist: create-dara-app (==1.25.1)
Requires-Dist: croniter (>=6.0.0,<7.0.0)
Requires-Dist: cryptography (>=42.0.4)
Requires-Dist: dara-components (==1.25.1) ; extra == "all"
Requires-Dist: exceptiongroup (>=1.1.3,<2.0.0)
Requires-Dist: fastapi (>=0.115.0,<0.121.0)
Requires-Dist: fastapi_vite_dara (==0.4.0)
Requires-Dist: h11 (>=0.16.0)
Requires-Dist: httpx (>=0.23.0)
Requires-Dist: jinja2 (>=2.1.1,<3.2.0)
Requires-Dist: jsonpatch (>=1.33)
Requires-Dist: odfpy
Requires-Dist: openpyxl
Requires-Dist: packaging (>=23.1)
Requires-Dist: pandas (>=1.1.0,<3.0.0)
Requires-Dist: prometheus-client (>=0.14.1,<1.0.0)
Requires-Dist: pyarrow
Requires-Dist: pydantic (>=2.11.7,<3.0.0)
Requires-Dist: pydantic-settings (>=2.8.1,<3.0.0)
Requires-Dist: pyjwt (>=2.3.0,<3.0.0)
Requires-Dist: python-dotenv (>=0.19.2)
Requires-Dist: python-multipart (>=0.0.7)
Requires-Dist: pyxlsb
Requires-Dist: responses (>=0.18.0,<0.19.0)
Requires-Dist: tblib (>=1.7.0,<2.0.0)
Requires-Dist: toml (>=0.10.2,<0.11.0)
Requires-Dist: typing-extensions (>=4.5.0)
Requires-Dist: uvicorn[standard] (>=0.23.1)
Requires-Dist: xlrd
Project-URL: Repository, https://github.com/causalens/dara
